Topsis_Muskan/Topsis.py
TOPSIS_Muskan_101803504-0.1.dist-info/LICENSE.txt
TOPSIS_Muskan_101803504-0.1.dist-info/METADATA
TOPSIS_Muskan_101803504-0.1.dist-info/WHEEL
TOPSIS_Muskan_101803504-0.1.dist-info/entry_points.txt
TOPSIS_Muskan_101803504-0.1.dist-info/top_level.txt
TOPSIS_Muskan_101803504-0.1.dist-info/RECORD
