Metadata-Version: 2.1
Name: TOPSIS-Muskan-101803504
Version: 0.1
Summary: A python package to implement TOPSIS on a given dataset
Home-page: UNKNOWN
Author: Muskan Gupta
Author-email: mgupta2_be18@thapar.edu
License: MIT
Platform: UNKNOWN
Classifier: License :: OSI Approved :: MIT License
Classifier: Programming Language :: Python :: 3
Classifier: Programming Language :: Python :: 3.4
Classifier: Programming Language :: Python :: 3.5
Classifier: Programming Language :: Python :: 3.6
Classifier: Programming Language :: Python :: 3.7
Requires-Dist: pandas
Requires-Dist: numpy
